sopel_rep/__init__.py
sopel_rep/errors.py
sopel_rep/manager.py
sopel_rep/plugin.py
sopel_rep-1.2.0.dist-info/licenses/COPYING
sopel_rep-1.2.0.dist-info/METADATA
sopel_rep-1.2.0.dist-info/WHEEL
sopel_rep-1.2.0.dist-info/entry_points.txt
sopel_rep-1.2.0.dist-info/top_level.txt
sopel_rep-1.2.0.dist-info/RECORD
